Metadata-Version: 1.0
Name: vimilocfromweb
Version: 1.0
Summary: vimilocfromweb
Home-page: https://vk.com/viva_viktoria29
Author: viktoria
Author-email: veronicamaximovna29@gmail.com
License: BSD
Platform: UNKNOWN
